{"getting_started.md":"BMPraE3U","guides_autodiff.md":"B_zsHaa7","guides_convergence_index.md":"BIrQci2R","guides_convergence_scalar-operators.md":"B6gi8fo0","guides_convergence_shape-parameter-bases.md":"CmWSSrju","guides_convergence_vector-operators.md":"BQ-yLIIU","guides_convergence_work-precision.md":"DUdBxfwT","guides_custom_operators.md":"BW8-ODDF","guides_lux.md":"BWKracSG","guides_operators.md":"Cuw_iovA","guides_pde_operators.md":"Dd6L-LYp","guides_quickref.md":"CleBGrf6","guides_vector_calculus.md":"DjYkLG08","index.md":"isejXu67","reference_api.md":"D6QwWRVV","reference_internals.md":"D_NIVmx1","reference_theory.md":"NIre4xJV"}
